vowcon/__init__.py
vowcon/vowcon.py
vowcon-0.0.1.dist-info/LICENSE.txt
vowcon-0.0.1.dist-info/METADATA
vowcon-0.0.1.dist-info/WHEEL
vowcon-0.0.1.dist-info/top_level.txt
vowcon-0.0.1.dist-info/RECORD
